debug.py
treerec/__init__.py
treerec/__main__.py
treerec/commands.py
treerec/dictutils.py
treerec/dirutils.py
treerec/entryutils.py
treerec/hist_events.py
treerec/navutils.py
treerec/pathtuputils.py
treerec/primitives.py
treerec/trace_ancestors.py
treerec/trcursor.py
treerec/treeobj.py
treerec/winutils.py
treerec/command_parser/__init__.py
treerec/command_parser/commandclass.py
treerec/command_parser/initutils.py
treerec/command_parser/madout.py
treerec/engine/__init__.py
treerec/engine/engine_base.py
treerec/engine/engine_pending.py
treerec-1.1.2.dist-info/LICENSE
treerec-1.1.2.dist-info/METADATA
treerec-1.1.2.dist-info/WHEEL
treerec-1.1.2.dist-info/top_level.txt
treerec-1.1.2.dist-info/RECORD
