Metadata-Version: 2.1
Name: treerec
Version: 1.1.2
Summary: A package for recording directory and file information.
Author: Joseph W. Merritt
Project-URL: Homepage, https://github.com/JWMerritt/treerec
Project-URL: Issues, https://github.com/JWMerritt/treerec/issues
Classifier: Programming Language :: Python :: 3
Classifier: License :: OSI Approved :: MIT License
Classifier: Operating System :: OS Independent
Requires-Python: >=3.9
License-File: LICENSE
